impose_cli/__init__.py
impose_cli/_utils.py
impose_cli/decorators.py
impose_cli/errors.py
impose_cli/impose_cli.py
tests/__init__.py
tests/simple.py
impose_cli-0.4.1.dist-info/LICENSE
impose_cli-0.4.1.dist-info/METADATA
impose_cli-0.4.1.dist-info/WHEEL
impose_cli-0.4.1.dist-info/top_level.txt
impose_cli-0.4.1.dist-info/RECORD
