Metadata-Version: 2.1
Name: impose-cli
Version: 0.4.1
Summary: Create a CLI tool easily.
Home-page: UNKNOWN
Author: scdev
Author-email: samuel.chai.development@gmail.com
License: UNKNOWN
Keywords: python,cli,click
Platform: UNKNOWN
Requires-Dist: click
Requires-Dist: docstring-parser
Requires-Dist: astor
